reject/__init__.py
reject/constant.py
reject/diversity.py
reject/reject.py
reject/uncertainty.py
reject/utils.py
reject-0.3.2.dist-info/LICENSE
reject-0.3.2.dist-info/METADATA
reject-0.3.2.dist-info/WHEEL
reject-0.3.2.dist-info/RECORD
