Metadata-Version: 2.1
Name: reject
Version: 0.3.2
Summary: Classification with rejection in Python.
Home-page: https://github.com/arthur-thuy/reject
License: Apache-2.0
Author: Arthur Thuy
Maintainer: Arthur Thuy
Maintainer-email: arthur.thuy@telenet.be
Requires-Python: >=3.9,<4.0
Classifier: Development Status :: 3 - Alpha
Classifier: License :: OSI Approved :: Apache Software License
Classifier: Operating System :: OS Independent
Classifier: Programming Language :: Python :: 3
Classifier: Programming Language :: Python :: 3.9
Classifier: Programming Language :: Python :: 3.10
Classifier: Programming Language :: Python :: 3.11
Classifier: Programming Language :: Python :: 3.12
Classifier: Topic :: Scientific/Engineering :: Artificial Intelligence
Requires-Dist: matplotlib (>=3.8.3,<4.0.0)
Requires-Dist: numpy (>=1.26.4,<2.0.0)
Requires-Dist: scipy (>=1.12.0,<2.0.0)
Project-URL: Documentation, https://reject.readthedocs.io
Project-URL: Repository, https://github.com/arthur-thuy/reject
